rllm/__init__.py
rllm/lib.py
relation_llm-0.0.1.dist-info/LICENSE
relation_llm-0.0.1.dist-info/METADATA
relation_llm-0.0.1.dist-info/WHEEL
relation_llm-0.0.1.dist-info/top_level.txt
relation_llm-0.0.1.dist-info/RECORD
