Metadata-Version: 2.1
Name: relation-llm
Version: 0.0.1
Summary: A package aiming to using LLM to analyse relational data. Still in developing.
Author-email: rllm_project <beckwangsns@gmail.com>
Project-URL: Homepage, https://github.com/rllm-project/rllm
Project-URL: Bug Tracker, https://github.com/rllm-project/rllm/issues
Classifier: Programming Language :: Python :: 3
Classifier: License :: OSI Approved :: MIT License
Classifier: Operating System :: OS Independent
Requires-Python: >=3.8
License-File: LICENSE
